setup.py
ri_distributions/Binomialdistribution.py
ri_distributions/Gaussiandistribution.py
ri_distributions/Generaldistribution.py
ri_distributions/__init__.py
ri_distributions.egg-info/PKG-INFO
ri_distributions.egg-info/SOURCES.txt
ri_distributions.egg-info/dependency_links.txt
ri_distributions.egg-info/not-zip-safe
ri_distributions.egg-info/top_level.txt